{
  "resourceType": "ValueSet",
  "status": "active",
  "name": "TnmPraefixVVS",
  "id": "tnm-qualifier-v",
  "title": "TNM Praefix V",
  "description": "Includes codes for TNM praefix V (Veneninvasion).",
  "version": "0.1.0",
  "url": "http://fhir.de/onkologie/ValueSet/tnm-qualifier-v",
  "compose": {
    "include": [
      {
        "system": "urn:oid:1.2.276.0.76.3.1.131.1.5.1",
        "concept": [
          {
            "code": "v",
            "display": "V"
          }
        ]
      }
    ]
  }
}
